Metadata-Version: 2.1
Name: FadeoutToSleep
Version: 1.0
Summary: A program to fade out volume linearly and put the computer to sleep.
Home-page: https://github.com/tekmiikka/fadeouttosleep
Author: TekMiikka
License: GPLv3
Project-URL: Homepage, https://github.com/tekmiikka/fadeouttosleep
Keywords: sleep,standby,volume,GTK,glade
Classifier: Programming Language :: Python :: 3
Classifier: License :: OSI Approved :: GNU General Public License v3 (GPLv3)
Classifier: Operating System :: POSIX :: Linux
Classifier: Topic :: Multimedia :: Sound/Audio :: Mixers
Classifier: Intended Audience :: End Users/Desktop
Requires-Python: >=3.4
License-File: LICENSE
